dial_gui/__init__.py
dial_gui/__main__.py
dial_gui/app.py
dial_gui/event_filters/__init__.py
dial_gui/event_filters/panning_event_filter.py
dial_gui/event_filters/resizable_item_event_filter.py
dial_gui/event_filters/zoom_event_filter.py
dial_gui/main_window/__init__.py
dial_gui/main_window/containers.py
dial_gui/main_window/main_menubar.py
dial_gui/main_window/main_window.py
dial_gui/node_editor/__init__.py
dial_gui/node_editor/context_menu.py
dial_gui/node_editor/graphics_connection.py
dial_gui/node_editor/graphics_node.py
dial_gui/node_editor/graphics_port.py
dial_gui/node_editor/graphics_scene.py
dial_gui/node_editor/node_editor_view.py
dial_gui/node_editor/node_editor_window.py
dial_gui/node_editor/type_colors.py
dial_gui/utils/__init__.py
dial_gui/utils/initialization.py
dial_gui/utils/tkinter.py
dial_gui/widgets/__init__.py
dial_gui/widgets/abstract_tree_model/__init__.py
dial_gui/widgets/abstract_tree_model/abstract_tree_model.py
dial_gui/widgets/log/__init__.py
dial_gui/widgets/log/containers.py
dial_gui/widgets/log/logger_dialog.py
dial_gui/widgets/log/logger_textbox.py
dial_gui/widgets/menus/__init__.py
dial_gui/widgets/menus/file_menu.py
dial_gui/widgets/menus/nodes_menu.py
dial-0.5a0.dist-info/LICENSE
dial-0.5a0.dist-info/METADATA
dial-0.5a0.dist-info/WHEEL
dial-0.5a0.dist-info/entry_points.txt
dial-0.5a0.dist-info/top_level.txt
dial-0.5a0.dist-info/RECORD
